cli_proxy_openstack-0.1.4.dist-info/DESCRIPTION.rst
cli_proxy_openstack-0.1.4.dist-info/METADATA
cli_proxy_openstack-0.1.4.dist-info/RECORD
cli_proxy_openstack-0.1.4.dist-info/WHEEL
cli_proxy_openstack-0.1.4.dist-info/entry_points.txt
cli_proxy_openstack-0.1.4.dist-info/metadata.json
cli_proxy_openstack-0.1.4.dist-info/top_level.txt
modules/__init__.py
modules/__main__.py
modules/connection.py
modules/router.py
modules/utils.py
