Metadata-Version: 2.0
Name: cli-proxy-openstack
Version: 0.1.4
Summary: CLI for Proxy Service integrated with OpenStack
Home-page: https://github.com/LamNguy/cli_pat
Author: Nguyen Duc Lam
Author-email: lamchipabc@gmail.com
License: UNKNOWN
Platform: UNKNOWN
Requires-Python: >=2.7
Requires-Dist: configparser
Requires-Dist: openstacksdk (==0.36.5)
Requires-Dist: pbr (>=2.0.0)
Requires-Dist: pick
Requires-Dist: prettytable
